{
  "addonType": "monitoring",
  "annotations": {
    "ingressSupported": "false",
    "source": "community",
    "contributor": "appdynamics"
  },
  "cloudTypes": [
    "all"
  ],
  "charts": [
    "charts/appdynamics-collectors-1.19.978.tgz"
  ],
  "displayName": "Cisco AppDynamics Collectors",
  "layer": "addon",
  "name": "cisco-appdynamics-collectors",
  "version": "1.19.978",
  "constraints": {
    "dependencies": [
      {
        "layer": "addon",
        "packName": "cisco-appdynamics-operators",
        "minVersion": "1.19.0",
        "maxVersion": "",
        "type": "required"
      }
    ]
  }
}
